futures3/__init__.py
futures3/_base.py
futures3/process.py
futures3/thread.py
futures3-1.0.0.dist-info/METADATA
futures3-1.0.0.dist-info/RECORD
futures3-1.0.0.dist-info/WHEEL
futures3-1.0.0.dist-info/top_level.txt
