Metadata-Version: 1.2
Name: futures3
Version: 1.0.0
Summary: The latest version for concurrent.futures package from Python 3
Home-page: https://github.com/mihaiparvu/futures3
Author: Brian Quinlan
Author-email: brian@sweetapp.com
Maintainer: Mihai Pârvu
Maintainer-email: mihaiparvu90@gmail.com
License: PSF
Platform: UNKNOWN
Classifier: License :: OSI Approved :: Python Software Foundation License
Classifier: Development Status :: 5 - Production/Stable
Classifier: Intended Audience :: Developers
Classifier: Programming Language :: Python :: 3.6
Classifier: Programming Language :: Python :: 3.7
Classifier: Programming Language :: Python :: 3 :: Only
Requires-Python: >3
